Metadata-Version: 1.0
Name: shevcdim-dsnd-distributions
Version: 0.1
Summary: Gaussian and binomial distributions classes
Home-page: UNKNOWN
Author: shevchuk dimitri
Author-email: UNKNOWN
License: UNKNOWN
Platform: UNKNOWN
